{
  "id": "concept/what-is-reconnaissance",
  "title": "What Is Reconnaissance?",
  "description": "Your write‑up here…",
  "source": "@site/docs/concept/what‑is‑reconnaissance.md",
  "sourceDirName": "concept",
  "slug": "/concept/what-is-reconnaissance",
  "permalink": "/docs/concept/what-is-reconnaissance",
  "draft": false,
  "unlisted": false,
  "editUrl": "https://github.com/ObsidianStrike/cybersec-writeups/tree/main/docs/concept/what‑is‑reconnaissance.md",
  "tags": [],
  "version": "current",
  "frontMatter": {
    "id": "what-is-reconnaissance",
    "title": "What Is Reconnaissance?",
    "sidebar_label": "Reconnaissance"
  },
  "sidebar": "tutorialSidebar",
  "previous": {
    "title": "Introduction",
    "permalink": "/docs/concept/intro"
  },
  "next": {
    "title": "Introduction",
    "permalink": "/docs/how-to/intro"
  }
}