{
  "/cybersec-writeups/markdown-page-09b": {
    "__comp": "1f391b9e",
    "__context": {
      "plugin": "a7456010"
    },
    "content": "393be207"
  },
  "/cybersec-writeups/docs-b9f": {
    "__comp": "5e95c892",
    "__context": {
      "plugin": "aba21aa0"
    }
  },
  "/cybersec-writeups/docs-b16": {
    "__comp": "a7bd4aaa",
    "__props": "8fd2a33a"
  },
  "/cybersec-writeups/docs-1fe": {
    "__comp": "a94703ab"
  },
  "/cybersec-writeups/docs/concept/intro-f81": {
    "__comp": "17896441",
    "content": "2abd47e8"
  },
  "/cybersec-writeups/docs/how-to/intro-8fd": {
    "__comp": "17896441",
    "content": "af9cb1a8"
  },
  "/cybersec-writeups/docs/reference/intro-2c5": {
    "__comp": "17896441",
    "content": "5a37071a"
  },
  "/cybersec-writeups/docs/tutorial/intro-9d2": {
    "__comp": "17896441",
    "content": "2e854b47"
  },
  "/cybersec-writeups/-e0a": {
    "__comp": "c4f5d8e4",
    "__context": {
      "plugin": "a7456010"
    },
    "config": "5e9f5e1a"
  }
}