{
  "/cybersec-writeups/404-322": {
    "__comp": "6bb41b40",
    "__context": {
      "plugin": "a7456010"
    },
    "config": "5e9f5e1a"
  },
  "/cybersec-writeups/docs-5fb": {
    "__comp": "5e95c892",
    "__context": {
      "plugin": "aba21aa0"
    }
  },
  "/cybersec-writeups/docs-d7c": {
    "__comp": "a7bd4aaa",
    "__props": "8fd2a33a"
  },
  "/cybersec-writeups/docs-d33": {
    "__comp": "a94703ab"
  },
  "/cybersec-writeups/docs/concept/intro-f81": {
    "__comp": "17896441",
    "content": "2abd47e8"
  },
  "/cybersec-writeups/docs/concept/what-is-reconnaissance-587": {
    "__comp": "17896441",
    "content": "943f46a6"
  },
  "/cybersec-writeups/docs/how-to/intro-8fd": {
    "__comp": "17896441",
    "content": "af9cb1a8"
  },
  "/cybersec-writeups/docs/intro-e50": {
    "__comp": "17896441",
    "content": "0e384e19"
  },
  "/cybersec-writeups/docs/reference/intro-2c5": {
    "__comp": "17896441",
    "content": "5a37071a"
  },
  "/cybersec-writeups/docs/tutorial/intro-9d2": {
    "__comp": "17896441",
    "content": "2e854b47"
  },
  "/cybersec-writeups/-e0a": {
    "__comp": "c4f5d8e4",
    "__context": {
      "plugin": "a7456010"
    },
    "config": "5e9f5e1a"
  }
}